zoil/__init__.py
zoil/well.py
zoil-0.0.4.dist-info/LICENSE
zoil-0.0.4.dist-info/METADATA
zoil-0.0.4.dist-info/WHEEL
zoil-0.0.4.dist-info/top_level.txt
zoil-0.0.4.dist-info/RECORD
