Metadata-Version: 2.1
Name: zoil
Version: 0.0.4
Summary: Generates random Oil and Gas Data
Home-page: UNKNOWN
Author: David Zajac
Author-email: davidzajac321@gmail.com
License: UNKNOWN
Keywords: python,oil,dca,reservoir engineering
Platform: UNKNOWN
Classifier: Development Status :: 1 - Planning
Classifier: Intended Audience :: Developers
Classifier: Programming Language :: Python :: 3
Classifier: Operating System :: Unix
Classifier: Operating System :: MacOS :: MacOS X
Classifier: Operating System :: Microsoft :: Windows
